byteripper/__init__.py
byteripper/cli.py
byteripper/core/__init__.py
byteripper/core/ai_cleanup.py
byteripper/core/ast_builder.py
byteripper/core/codegen.py
byteripper/core/decompiler.py
byteripper/core/loader.py
byteripper/core/magic.py
byteripper/core/obfuscation.py
byteripper/core/opcodes.py
byteripper/data/__init__.py
byteripper-1.0.0.dist-info/licenses/LICENSE
byteripper-1.0.0.dist-info/METADATA
byteripper-1.0.0.dist-info/WHEEL
byteripper-1.0.0.dist-info/entry_points.txt
byteripper-1.0.0.dist-info/top_level.txt
byteripper-1.0.0.dist-info/RECORD
