Metadata-Version: 2.4
Name: byteripper
Version: 1.0.0
Summary: python bytecode decompiler - convert pyc to py
Author-email: mero <mero@byteripper.dev>
License: MIT
Project-URL: Homepage, https://github.com/6x-u/byteripper
Project-URL: Repository, https://github.com/6x-u/byteripper
Project-URL: Issues, https://github.com/6x-u/byteripper/issues
Keywords: pyc,decompiler,bytecode,python,reverse-engineering,disassembler
Classifier: Development Status :: 4 - Beta
Classifier: Intended Audience :: Developers
Classifier: License :: OSI Approved :: MIT License
Classifier: Operating System :: OS Independent
Classifier: Programming Language :: Python :: 3
Classifier: Programming Language :: Python :: 3.5
Classifier: Programming Language :: Python :: 3.6
Classifier: Programming Language :: Python :: 3.7
Classifier: Programming Language :: Python :: 3.8
Classifier: Programming Language :: Python :: 3.9
Classifier: Programming Language :: Python :: 3.10
Classifier: Programming Language :: Python :: 3.11
Classifier: Programming Language :: Python :: 3.12
Classifier: Programming Language :: Python :: 3.13
Classifier: Programming Language :: Python :: 3.14
Classifier: Topic :: Software Development :: Disassemblers
Classifier: Topic :: Software Development :: Libraries :: Python Modules
Requires-Python: >=3.5
License-File: LICENSE
Requires-Dist: g4f>=6.7.0
Requires-Dist: setuptools>=50.3.2
Provides-Extra: ai
Requires-Dist: g4f; extra == "ai"
Dynamic: license-file
